<annotation>
  <folder>images</folder>
  <filename>outlet_000633</filename>
  <path>/home/christinelee/thesis/training/images/outlet_000633.JPEG</path>
  <source>
    <database>Unknown</database>
  </source>
  <size>
    <width>400</width>
    <height>400</height>
    <depth>3</depth>
  </size>
  <segmented>0</segmented>
  <object>
    <name>outlet</name>
    <pose>Unspecified</pose>
    <truncated>0</truncated>
    <difficult>0</difficult>
    <bndbox>
      <xmin>260</xmin>
      <ymin>200</ymin>
      <xmax>309</xmax>
      <ymax>256</ymax>
    </bndbox>
  </object>
</annotation>
