<annotation>
  <folder>images</folder>
  <filename>outlet_000138</filename>
  <path>/home/christinelee/thesis/training/images/outlet_000138.JPEG</path>
  <source>
    <database>Unknown</database>
  </source>
  <size>
    <width>3456</width>
    <height>2592</height>
    <depth>3</depth>
  </size>
  <segmented>0</segmented>
  <object>
    <name>outlet</name>
    <pose>Unspecified</pose>
    <truncated>0</truncated>
    <difficult>0</difficult>
    <bndbox>
      <xmin>963</xmin>
      <ymin>1570</ymin>
      <xmax>1066</xmax>
      <ymax>1688</ymax>
    </bndbox>
  </object>
  <object>
    <name>outlet</name>
    <pose>Unspecified</pose>
    <truncated>0</truncated>
    <difficult>0</difficult>
    <bndbox>
      <xmin>970</xmin>
      <ymin>1740</ymin>
      <xmax>1070</xmax>
      <ymax>1858</ymax>
    </bndbox>
  </object>
  <object>
    <name>outlet</name>
    <pose>Unspecified</pose>
    <truncated>0</truncated>
    <difficult>0</difficult>
    <bndbox>
      <xmin>2337</xmin>
      <ymin>1466</ymin>
      <xmax>2418</xmax>
      <ymax>1573</ymax>
    </bndbox>
  </object>
  <object>
    <name>outlet</name>
    <pose>Unspecified</pose>
    <truncated>0</truncated>
    <difficult>0</difficult>
    <bndbox>
      <xmin>2340</xmin>
      <ymin>1618</ymin>
      <xmax>2433</xmax>
      <ymax>1733</ymax>
    </bndbox>
  </object>
</annotation>
